cleaner/__init__.py
cleaner/__main__.py
cleaner/app.py
cleaner/credentials.py
cleaner/docker_project.py
cleaner/repository.py
cleaner/tag.py
docker_registry_cleaner-0.1.0.dist-info/DESCRIPTION.rst
docker_registry_cleaner-0.1.0.dist-info/METADATA
docker_registry_cleaner-0.1.0.dist-info/RECORD
docker_registry_cleaner-0.1.0.dist-info/WHEEL
docker_registry_cleaner-0.1.0.dist-info/entry_points.txt
docker_registry_cleaner-0.1.0.dist-info/metadata.json
docker_registry_cleaner-0.1.0.dist-info/top_level.txt
