Metadata-Version: 2.0
Name: docker-registry-cleaner
Version: 0.1.0
Summary: A tool to remove unused images from a Docker registry
Home-page: https://github.com/yodle/Docker-Registry-Cleaner
Author: John Downs
Author-email: john.downs@yodle.com
License: Apache 2.0
Keywords: docker docker-registry
Platform: UNKNOWN
Classifier: Development Status :: 3 - Alpha
Classifier: Intended Audience :: Developers
Classifier: Topic :: Software Development :: Build Tools
Classifier: License :: OSI Approved :: Apache Software License
Classifier: Programming Language :: Python :: 2.7
Classifier: Programming Language :: Python :: 3.5
Provides-Extra: dev
Provides-Extra: test
